hypernetx/__init__.py
hypernetx/exception.py
hypernetx/read_write.py
hypernetx/algorithms/__init__.py
hypernetx/algorithms/homology_mod2.py
hypernetx/algorithms/s_centrality_measures.py
hypernetx/classes/__init__.py
hypernetx/classes/entity.py
hypernetx/classes/hypergraph.py
hypernetx/classes/staticentity.py
hypernetx/classes/untitled-centrality.py
hypernetx/drawing/__init__.py
hypernetx/drawing/rubber_band.py
hypernetx/drawing/two_column.py
hypernetx/drawing/util.py
hypernetx/reports/__init__.py
hypernetx/reports/descriptive_stats.py
hypernetx/utils/__init__.py
hypernetx/utils/decorators.py
hypernetx/utils/extras.py
hnxbeta-0.1.18.dist-info/LICENSE.rst
hnxbeta-0.1.18.dist-info/METADATA
hnxbeta-0.1.18.dist-info/WHEEL
hnxbeta-0.1.18.dist-info/top_level.txt
hnxbeta-0.1.18.dist-info/RECORD
